unrelatedLibraries/__init__.py
unrelatedlibraries-0.0.1.dist-info/METADATA
unrelatedlibraries-0.0.1.dist-info/WHEEL
unrelatedlibraries-0.0.1.dist-info/top_level.txt
unrelatedlibraries-0.0.1.dist-info/RECORD
