Metadata-Version: 2.4
Name: unrelatedLibraries
Version: 0.0.1
Summary: This is a package for demonstration purposes.
Author: temp try
Dynamic: author
Dynamic: description-content-type
Dynamic: summary
